elasticpedia/__init__.py
elasticpedia/cli.py
elasticpedia/elasticpedia.py
elasticpedia/config/__init__.py
elasticpedia/config/elastic_conf.py
elasticpedia/config/spark_conf.py
elasticpedia/reader/__init__.py
elasticpedia/reader/dbpedia_reader.py
elasticpedia/spark/__init__.py
elasticpedia/spark/session.py
elasticpedia/utils/__init__.py
elasticpedia/utils/string_utils.py
elasticpedia-1.0.1.dist-info/AUTHORS.rst
elasticpedia-1.0.1.dist-info/LICENSE
elasticpedia-1.0.1.dist-info/METADATA
elasticpedia-1.0.1.dist-info/WHEEL
elasticpedia-1.0.1.dist-info/entry_points.txt
elasticpedia-1.0.1.dist-info/top_level.txt
elasticpedia-1.0.1.dist-info/RECORD
