Metadata-Version: 2.1
Name: elasticpedia
Version: 1.0.1
Summary: Indexing DBpedia with Elasticsearch.
Home-page: https://github.com/vcutrona/elasticpedia
Author: Vincenzo Cutrona
Author-email: v.cutrona1@gmail.com
License: Apache Software License 2.0
Keywords: elasticpedia
Platform: UNKNOWN
Classifier: Development Status :: 5 - Production/Stable
Classifier: Intended Audience :: Developers
Classifier: License :: OSI Approved :: Apache Software License
Classifier: Natural Language :: English
Classifier: Programming Language :: Python :: 3
Classifier: Programming Language :: Python :: 3.6
Classifier: Programming Language :: Python :: 3.7
Requires-Python: >=3.6, <3.8
Requires-Dist: Click (>=7.0)
Requires-Dist: pyspark (==2.4.4)
